[
    {
        "device_id": "054a7c205fbde8b6",
        "key": "Key-FAZA-5388372672",
        "expirydate": "31-12-2029",
        "Allowoffline": true
    },
    {
        "device_id": "5645f7639bcf9562",
        "key": "5645f7639bcf9562",
        "expirydate": "15-11-2029",
        "Allowoffline": false
    },
    {
        "device_id": "aaf0710ca72f4006",
        "key": "aaf0710ca72f4006",
        "expirydate": "15-11-2029",
        "Allowoffline": false
    },
    {
        "device_id": "3b04790787848c82",
        "key": "Key-koki-3b04790787848c82",
        "expirydate": "15-11-2029",
        "Allowoffline": false
    },
    {
        "device_id": "07c33bc8bd8ba0c5",
        "key": "Key-saifing-07c33bc8bd8ba0c5",
        "expirydate": "15-11-2029",
        "Allowoffline": false
    },
    {
        "device_id": "f3019ee87eb15f29",
        "key": "Key-saifing-f3019ee87eb15f29",
        "expirydate": "15-11-2029",
        "Allowoffline": false
    },
    {
        "device_id": "95f0f1dcf80f97c1",
        "key": "Key-Verkyut-95f0f1dcf80f97c1",
        "expirydate": "15-11-2029",
        "Allowoffline": false
    },
    {
        "device_id": "f11c39bb36516541",
        "key": "Key-Lia-f11c39bb36516541",
        "expirydate": "15-11-2029",
        "Allowoffline": false
    },
    {
        "device_id": "8719ebe948ae6071",
        "key": "Nico-8719ebe948ae6071",
        "expirydate": "15-11-2029",
        "Allowoffline": false
    }
    
]
